pyinfra_ansible_inventory_connector/__init__.py
pyinfra_ansible_inventory_connector/connector.py
pyinfra_ansible_inventory_connector-0.1.1.dist-info/METADATA
pyinfra_ansible_inventory_connector-0.1.1.dist-info/WHEEL
pyinfra_ansible_inventory_connector-0.1.1.dist-info/entry_points.txt
pyinfra_ansible_inventory_connector-0.1.1.dist-info/licenses/LICENSE
pyinfra_ansible_inventory_connector-0.1.1.dist-info/RECORD
