Metadata-Version: 2.4
Name: pyinfra-ansible-inventory-connector
Version: 0.1.1
Summary: Ansible inventory connector for pyinfra 3.x
Project-URL: Homepage, https://github.com/j-jacobsen/pyinfra-ansible-inventory-connector
Author-email: Julian Jacobsen <jj@compositiv.com>
License: MIT
License-File: LICENSE
Requires-Python: >=3.9
Requires-Dist: ansible-core>=2.14
Requires-Dist: pyinfra>=3.0
